StatViz/__init__.py
StatViz/statviz.py
StatViz-0.0.2.dist-info/METADATA
StatViz-0.0.2.dist-info/WHEEL
StatViz-0.0.2.dist-info/top_level.txt
StatViz-0.0.2.dist-info/RECORD
