Metadata-Version: 2.1
Name: StatViz
Version: 0.0.2
Author: Namitha Kolu and Ashok Kumar S
Requires-Dist: pandas
Requires-Dist: seaborn
Requires-Dist: openpyxl
Requires-Dist: numpy
Requires-Dist: setuptools
